{"0": "AM_dept", "1": "BE_dept", "2": "BE_dept_HOD", "3": "CE_dept", "4": "CE_dept_HOD", "5": "CSE_dept", "6": "CSE_dept_HOD", "7": "ChE_Dept", "8": "ChE_Dept_HOD", "9": "Department", "10": "Director", "11": "ECE_dept", "12": "ECE_dept_HOD", "13": "EE_dept", "14": "EE_dept_HOD", "15": "ME_dept", "16": "ME_dept_HOD", "17": "PIE_dept", "18": "PIE_dept_HOD", "19": "affirm", "20": "ask_about_exam_preparation_tips", "21": "ask_about_faculty", "22": "ask_about_fees", "23": "ask_about_grading_system", "24": "ask_about_healthcare_facilities", "25": "ask_about_hostel_facilities", "26": "ask_about_internship_opportunities", "27": "ask_about_lab_facilities", "28": "ask_about_library", "29": "ask_about_mentorship_program", "30": "ask_admission_process", "31": "ask_for_directions", "32": "ask_intro_format", "33": "ask_placements", "34": "benfit_of_the_club", "35": "bot_challenge", "36": "boys_hostel", "37": "cafe_96", "38": "cafe_96_location", "39": "cafetarea", "40": "club", "41": "college_playground", "42": "courses", "43": "dean", "44": "deny", "45": "dwesis_canteen", "46": "dwesis_location", "47": "explore_campus", "48": "girls_hostel", "49": "goodbye", "50": "greet", "51": "lit_club", "52": "mnnit_website", "53": "mobile_number", "54": "mood_great", "55": "mood_unhappy", "56": "more_about_college", "57": "my_name", "58": "robotics_club", "59": "yamuna_canteen", "60": "yamuna_location"}