{"0": "affirm", "1": "ask_about_exam_preparation_tips", "2": "ask_about_faculty", "3": "ask_about_fees", "4": "ask_about_grading_system", "5": "ask_about_hostel_facilities", "6": "ask_about_internship_opportunities", "7": "ask_about_lab_facilities", "8": "ask_about_library", "9": "ask_about_mentorship_program", "10": "ask_admission_process", "11": "ask_hostel_choice", "12": "ask_intro_format", "13": "ask_placements", "14": "bot_challenge", "15": "courses", "16": "deny", "17": "goodbye", "18": "greet", "19": "mnnit_website", "20": "mobile_number", "21": "mood_great", "22": "mood_unhappy", "23": "my_name"}